invian/__init__.py
invian/analysis/__init__.py
invian/analysis/analysis.py
invian/core/__init__.py
invian/core/photometry.py
invian/io/__init__.py
invian/io/nexfile.py
invian/io/nexio.py
invian-0.0.3.dist-info/LICENSE
invian-0.0.3.dist-info/METADATA
invian-0.0.3.dist-info/WHEEL
invian-0.0.3.dist-info/top_level.txt
invian-0.0.3.dist-info/RECORD
