Metadata-Version: 2.1
Name: invian
Version: 0.0.3
Summary: Package to analyze in vivo neural data
Author-email: Alex Legaria <leg.alex96@gmail.com>
License: GNU GENERAL PUBLIC LICENSE
Project-URL: Home, https://github.com/AlexLM96/invian
Keywords: neuroscience,electrophysiology,research
Classifier: License :: OSI Approved :: GNU General Public License v3 (GPLv3)
Classifier: Development Status :: 3 - Alpha
Classifier: Intended Audience :: Science/Research
Classifier: Programming Language :: Python :: 3
Requires-Python: >=3.6
License-File: LICENSE
Requires-Dist: pandas
Requires-Dist: numpy
Requires-Dist: scipy
Requires-Dist: matplotlib
Requires-Dist: seaborn
Requires-Dist: scikit-learn
